{
  "data" : {
    "lookups" : [
      "free-text",
      "keywords"
    ],
    "name" : "rejection",
    "lang" : "nb",
    "exotic" : false,
    "id" : "rejection",
    "values" : [
      {
        "value" : "Det er ikke nødvendig med mer data",
        "expressions" : [
          "Det er ikke nødvendig med mer data"
        ]
      },
      {
        "value" : "Det trenger jeg ikke",
        "expressions" : [
          "Det trenger jeg ikke"
        ]
      },
      {
        "value" : "Hun overlever uten",
        "expressions" : [
          "Hun overlever uten"
        ]
      },
      {
        "value" : "Jeg trenger ikke",
        "expressions" : [
          "Jeg trenger ikke"
        ]
      },
      {
        "value" : "Nei",
        "expressions" : [
          "Nei"
        ]
      },
      {
        "value" : "Nei, det er feil",
        "expressions" : [
          "Nei, det er feil"
        ]
      },
      {
        "value" : "Nei, det er ingen av de nummerene",
        "expressions" : [
          "Nei, det er ingen av de nummerene"
        ]
      },
      {
        "value" : "feil",
        "expressions" : [
          "feil"
        ]
      },
      {
        "value" : "slutt med dette",
        "expressions" : [
          "slutt med dette"
        ]
      },
      {
        "value" : "stop",
        "expressions" : [
          "stop"
        ]
      }
    ],
    "doc" : "User-defined entity",
    "builtin" : false
  }
}